puentessantiago/__init__.py
puentessantiago/matematicas.py
puentessantiago-0.1.0.dist-info/METADATA
puentessantiago-0.1.0.dist-info/WHEEL
puentessantiago-0.1.0.dist-info/RECORD
