Metadata-Version: 2.1
Name: puentessantiago
Version: 0.1.0
Summary: Paquete de ejemplo
Author: Santiago Quiñones
Author-email: lsquinones@gmail.com
Requires-Python: >=3.10.0,<3.12
Classifier: Programming Language :: Python :: 3
Classifier: Programming Language :: Python :: 3.10
Classifier: Programming Language :: Python :: 3.11
